Workbook

Sheet Scenario & Weights
A1: M6.6 | Scenario-weighted financial lens
A2: All M6.2 numbers are modeled API billings, not actual revenue. Weights below are purely illustrative judgment calls.
A4: Scenario | B4: Year-1 API billings ($) | C4: Year-1 after-referral-fee ($) | D4: Illustrative weight | E4: Weighted API billings ($) | F4: Weighted after-fee ($) | G4: Source | H4: Evidence grade
A5: Conservative | B5: 1523.9882 | C5: 1516.3683 | D5: 0.6 | E5: =B5*D5 -> 914.39292 | F5: =C5*D5 -> 909.82095 | G5: M6.2 Executive Summary | H5: Unverified scenario
A6: Base | B6: 125411.94 | C6: 123154.52 | D6: 0.35 | E6: =B6*D6 -> 43894.178 | F6: =C6*D6 -> 43104.083 | G6: M6.2 Executive Summary | H6: Unverified scenario
A7: Expansion | B7: 2384434.1 | C7: 2289056.7 | D7: 0.05 | E7: =B7*D7 -> 119221.7 | F7: =C7*D7 -> 114452.84 | G7: M6.2 Executive Summary | H7: Unverified scenario
A9: ILLUSTRATIVE WEIGHTED TOTAL | D9: =SUM(D5:D7) -> 1 | E9: =SUM(E5:E7) -> 164030.27 | F9: =SUM(F5:F7) -> 158466.74
A11: Weight validation | D11: =IF(ABS(D9-1)<0.00001,"PASS","FIX: weights must sum to 100%") -> PASS
A16: Stress setting | B16: Value | C16: Reason / source
A17: Realized workflow volume factor | B17: 0.75 | C17: Illustrative downside to M6.2 base forecast
A18: Realized negotiated price factor | B18: 0.9 | C18: Illustrative additional realization sensitivity
A19: Base year-1 API billings ($) | B19: =B6 -> 125411.94
A20: Downside-stressed base billings ($) | B20: =B19*B17*B18 -> 84653.057
A21: Billings difference ($) | B21: =B20-B19 -> -40758.879
A23: Use either a weighted scenario view OR an explicit downside case for decisions. Do not stack risk factors on top of already-downside inputs without confirming they are independent.

Sheet Revenue Sensitivity
A1: Revenue sensitivity | What moves the business case
A2: M6.2 base first-year API billings are stressed by independent changes in workflow volume and price realization.
A4: M6.2 base year-1 API billings ($) | B4: ='Scenario & Weights'!B6 -> 125411.94
A6: Volume factor × price factor | C6: 0.6 | D6: 0.75 | E6: 0.9 | F6: 1 | G6: 1.2
B7: 0.5 | C7: =$B$4*$B7*C$6 -> 37623.581 | D7: =$B$4*$B7*D$6 -> 47029.476 | E7: =$B$4*$B7*E$6 -> 56435.371 | F7: =$B$4*$B7*F$6 -> 62705.968 | G7: =$B$4*$B7*G$6 -> 75247.162
B8: 0.75 | C8: =$B$4*$B8*C$6 -> 56435.371 | D8: =$B$4*$B8*D$6 -> 70544.214 | E8: =$B$4*$B8*E$6 -> 84653.057 | F8: =$B$4*$B8*F$6 -> 94058.952 | G8: =$B$4*$B8*G$6 -> 112870.74
B9: 1 | C9: =$B$4*$B9*C$6 -> 75247.162 | D9: =$B$4*$B9*D$6 -> 94058.952 | E9: =$B$4*$B9*E$6 -> 112870.74 | F9: =$B$4*$B9*F$6 -> 125411.94 | G9: =$B$4*$B9*G$6 -> 150494.32
B10: 1.25 | C10: =$B$4*$B10*C$6 -> 94058.952 | D10: =$B$4*$B10*D$6 -> 117573.69 | E10: =$B$4*$B10*E$6 -> 141088.43 | F10: =$B$4*$B10*F$6 -> 156764.92 | G10: =$B$4*$B10*G$6 -> 188117.9
B11: 1.5 | C11: =$B$4*$B11*C$6 -> 112870.74 | D11: =$B$4*$B11*D$6 -> 141088.43 | E11: =$B$4*$B11*E$6 -> 169306.11 | F11: =$B$4*$B11*F$6 -> 188117.9 | G11: =$B$4*$B11*G$6 -> 225741.49
A14: A 25% shortfall in workflows and a 10% reduction in realized API pricing produce a different result from the published base case. This sensitivity is not a predictive demand distribution.
A17: Month-12 base paying ISVs | B17: 50
A18: Base Month-12 annualized API billings ($) | B18: 268849
A19: Target annualized API billings ($) | B19: 1000000
A20: Required base-equivalent ISVs | B20: =ROUNDUP(B19/(B18/B17),0) -> 186
A21: Required monthly workflow volume | B21: =B20*30000 -> 5580000
A23: M6.2 base includes 30,000 monthly workflows per ISV at Month 12. 186 ISVs is a scale equivalence, not validated market penetration or a sales forecast.

Sheet Pilot Capacity
A1: 90-day exploratory capacity | Allocation, not authorization
A2: Editable staff-time and fully loaded cost *hypotheses*; Anthropic finance must replace every assumed rate.
A4: Workstream | B4: FTE fraction | C4: Months | D4: Illustrative loaded cost / FTE-month ($) | E4: Modeled 90-day resource cost ($) | F4: Evidence to deliver | G4: Owner confirmed? | H4: Rate status
A5: Product / market discovery | B5: 0.5 | C5: 3 | D5: 30000 | E5: =B5*C5*D5 -> 45000 | F5: External buyer/developer research | G5: No | H5: Illustrative only
A6: Developer relations / ISV | B6: 0.5 | C6: 3 | D6: 25000 | E6: =B6*C6*D6 -> 37500 | F6: Developer onboarding and workflow validation | G6: No | H6: Illustrative only
A7: Solutions / evaluation eng. | B7: 0.25 | C7: 3 | D7: 30000 | E7: =B7*C7*D7 -> 22500 | F7: Paired benchmark and platform fit | G7: No | H7: Illustrative only
A8: Privacy / enterprise review | B8: 0.25 | C8: 3 | D8: 35000 | E8: =B8*C8*D8 -> 26250 | F8: BAA, channel and data-flow gate | G8: No | H8: Illustrative only
A10: Incremental API / test spend ($) | D10: 5000
A11: Estimated capacity envelope ($) | E11: =SUM(E5:E8)+D10 -> 136250
A12: FTE-month equivalents | E12: =SUMPRODUCT(B5:B8,C5:C8) -> 4.5
A13: Authorization status | E13: NOT AUTHORIZED
A18: Decision | B18: Requested authorization | C18: Not authorized
A19: 0–90 day validation | B19: Bounded exploration / capacity review | C19: Large integration build or commercial launch
A20: 90–180 day expansion | B20: Only if gates pass | C20: Production PHI without approvals

Sheet Risk Register
A1: Risk-adjusted investment decision | Eight material risks
A2: Scores are analyst judgments; likelihood is not a measured event probability.
A4: Risk | B4: Primary exposure | C4: Likelihood (1-5) | D4: Impact (1-5) | E4: Risk priority | F4: Mitigation / evidence | G4: Stop or escalation trigger | H4: Status
A5: No external buyer demand | B5: Revenue / product-market fit | C5: 4 | D5: 5 | E5: =C5*D5 -> 20 | F5: 6–8 discovery interviews, named sponsor | G5: No credible buyer / workflow sponsor after outreach | H5: Unvalidated
A6: Low recurring token volume | B6: Growth / monetization | C6: 4 | D6: 5 | E6: =C6*D6 -> 20 | F6: Observe volume and total cost per accepted workflow | G6: No sustainable usage at customer ROI | H6: Unvalidated
A7: Incumbent AI differentiation | B7: Competitive | C7: 4 | D7: 4 | E7: =C7*D7 -> 16 | F7: Blind matched eval against GPT/Gemini/no-AI | G7: No differentiation or inferior safety/cost | H7: Unvalidated
A8: Clinical safety / intended use | B8: Patient risk / regulatory | C8: 3 | D8: 5 | E8: =C8*D8 -> 15 | F8: High-severity eval, clinician signoff, intended-use review | G8: Any unresolved high-severity failure | H8: Unvalidated
A9: PHI + cloud channel eligibility | B9: Legal / data processing | C9: 4 | D9: 5 | E9: =C9*D9 -> 20 | F9: Validate BAA, service/operator, tools and subprocessors | G9: No approved end-to-end PHI architecture | H9: Unvalidated
A10: Partner/distribution dependency | B10: GTM / control | C10: 3 | D10: 4 | E10: =C10*D10 -> 12 | F10: Direct API first, assess channel after demand | G10: Exclusive access or unexpected channel costs | H10: Unvalidated
A11: Billing / revenue attribution | B11: Financial controls | C11: 3 | D11: 4 | E11: =C11*D11 -> 12 | F11: Actual event reconciliation before live billing | G11: Unexplained metering/settlement discrepancies | H11: Unvalidated
A12: Unvalidated internal economics | B12: Investment efficiency | C12: 4 | D12: 4 | E12: =C12*D12 -> 16 | F12: Finance-owned inference and loaded cost model | G12: Negative contribution at observed workloads | H12: Unvalidated

Sheet Investment Gates
A1: Gated executive decision | GO / ITERATE / STOP
A2: Day 90 can validate whether to fund a controlled pilot; paid production conversion belongs at Day 180 or later.
A4: Gate | B4: Proposed evidence threshold | C4: GO | D4: ITERATE | E4: STOP | F4: Owner | G4: Evidence status | H4: Decision
A5: Buyer / developer demand | B5: At least 6–8 interviews, 2 specific frequent workflows with documented buyer/sponsor | C5: Real sponsor and recurring problem | D5: Promising but workflow/buyer unclear | E5: No validated sponsor or ROI | F5: GTM / PM | G5: Not yet observed | H5: Pending
A6: Matched model evaluation | B6: Blinded current-model + no-AI comparator; predefined clinically reviewed error, traceability and review-time metrics | C6: Acceptable error and differentiated ROI | D6: Some quality/cost questions remain | E6: Unacceptable serious error or no value | F6: Evaluation / Clinical | G6: Not yet observed | H6: Pending
A7: Economics | B7: Observed tokens, clinician minutes and workflow volumes; internal servicing cost where available | C7: Attractive ROI and plausible recurring use | D7: Need narrower use case or pricing | E7: Structurally uneconomic at realistic usage | F7: PM / Finance | G7: Not yet observed | H7: Pending
A8: Enterprise deployment | B8: Actual channel/operator/BAA/feature coverage, data flows and safety scope reviewed | C8: Approved architecture for planned test | D8: Only synthetic data until approvals | E8: PHI handling blocked / unacceptable risk | F8: Security / Legal | G8: Not yet observed | H8: Pending
A9: Partner commercialization | B9: Defined direct/cloud accounting without duplicate billings; no unapproved resell terms | C9: Clear accountable buyer and route | D9: Procurement route pending | E9: Channel cannot support target customer | F9: Partnerships | G9: Not yet observed | H9: Pending
A10: Day-180 production proof | B10: Real paid non-test consumption, retention measured in mature cohorts | C10: Scale pathway credible | D10: Iterate onboarding/offer | E10: No paid usage or material risk | F10: GTM / Sales | G10: Not yet observed | H10: Pending

Sheet Evidence & Sources
A1: M6.6 evidence inventory | What is known versus hypothesized
A4: Claim class | B4: Evidence | C4: Limitation | D4: Source path / link | E4: Evidence grade | F4: Owner | G4: Last checked | H4: Data type
A5: Completed local build | B5: ChartGround M1–M5: API, metering, budget, invoicing simulation, dashboard; 151 offline tests | C5: No paid customer, deployment or enterprise approval | D5: ChartGround M1–M5 milestone log | E5: Locally tested | F5: Project | G5: 2026-10-29 | H5: Observed local
A6: Market selection | B6: Clinical workflow ISVs lead weighted M6.1 scorecard; oncology first specialty | C6: Secondary research; overlapped categories and subjective weights | D6: ChartGround_M6_1_Healthcare_Market_Selection_Analysis.xlsx | E6: Analyst scored | F6: M6.1 | G6: 2026-10-29 | H6: Research / hypothesis
A7: Modeled billings | B7: First-year $1.5K / $125.4K / $2.384M conservative/base/expansion | C7: Assumed adoption, workflows, model mix, token sizes and discounts | D7: ChartGround_M6_2_Healthcare_API_Monetization_Revenue_Model.xlsx | E7: Model only | F7: M6.2 | G7: 2026-10-29 | H7: Hypothesis
A8: Developer funnel | B8: M6.3 proposes first call -> evaluation -> pilot -> paying production | C8: No observed external ISV conversion cohort | D8: ChartGround_M6_3_Developer_Adoption_Funnel_and_Roadmap.xlsx | E8: Proposed targets | F8: M6.3 | G8: 2026-10-29 | H8: Hypothesis
A9: Buyer landscape | B9: 20 real researched companies; six discovery hypotheses | C9: No outreach, buyer interest or Claude model adoption verified | D9: ChartGround_M6_4_Healthcare_Target_Accounts_Enterprise_Readiness.xlsx | E9: Public research | F9: M6.4 | G9: 2026-10-29 | H9: Secondary research
A10: Competition / partners | B10: Citation feature and cloud distribution pathways; comparison benchmark required | C10: No head-to-head current-model evaluation and no new signed partners | D10: ChartGround_M6_5_Competitive_Positioning_Partner_Strategy.xlsx | E10: Public research | F10: M6.5 | G10: 2026-10-29 | H10: Secondary research
A11: Native citation caveat | B11: Claude citation blocks and strict structured outputs incompatible in same request | C11: Architectural solution must be tested | D11: https://platform.claude.com/docs/en/build-with-claude/citations | E11: Official docs | F11: Anthropic | G11: 2026-10-29 | H11: External
A12: Deployment gate | B12: Different BAA/channel and eligible-feature requirements apply | C12: Must verify actual signed agreements and architecture | D12: https://docs.aws.amazon.com/claude-platform/latest/userguide/cpa-vs-bedrock.html | E12: Official docs | F12: AWS | G12: 2026-10-29 | H12: External
A13: Existing partner route | B13: TCS / Anthropic regulated-industry partnership publicly announced | C13: Does not constitute a ChartGround partner relationship | D13: https://www.anthropic.com/news/tcs-anthropic-partnership | E13: Official announcement | F13: Anthropic | G13: 2026-10-29 | H13: External

Sheet Executive Summary
A1: M6.6 | Executive decision dashboard
A4: Decision lens | B4: Key value | C4: Interpretation | D4: Evidence basis
A5: M6.2 base year-1 API billings ($) | B5: ='Scenario & Weights'!B6 -> 125411.94 | C5: Illustrative adoption and consumption only
A6: M6.2 base month-12 annualized ($) | B6: 268849 | C6: Run rate, not realized year-one revenue
A7: Illustrative scenario-weighted year-1 billings ($) | B7: ='Scenario & Weights'!E9 -> 164030.27 | C7: 60%/35%/5% analyst weights; not empirical likelihoods
A8: Downside-stressed base year-1 billings ($) | B8: ='Scenario & Weights'!B20 -> 84653.057 | C8: 75% workflow × 90% realized price sensitivity
A9: M6.2 $1M run-rate ISV equivalence | B9: ='Revenue Sensitivity'!B20 -> 186 | C9: Assumes M6.2 base per-ISV intensity, not sales forecast
A12: Investment stance | B12: Authorization boundary | C12: Validation gate
A13: Approve now | B13: Discovery, blinded evaluation, channel/security review | C13: Named accountable owner; bounded capacity / Finance review
A14: Withhold | B14: Broad launch, reseller commitments, PHI deployment | C14: No external buyer, validated performance or end-to-end approval yet
A15: Day 90 decision | B15: GO / ITERATE / STOP pilot funding | C15: Based on interview, benchmark and economics evidence
A16: Day 180 decision | B16: Paid-production and sustained usage assessment | C16: Only real production events—not ChartGround demos
